setup.py
mobileclick/__init__.py
mobileclick/index.py
mobileclick/index_factory.py
mobileclick/intent.py
mobileclick/iunit.py
mobileclick/measurable.py
mobileclick/query.py
mobileclick/ranking_run.py
mobileclick/run.py
mobileclick/summarization_run.py
mobileclick/summary.py
mobileclick/summary_error.py
mobileclick/task.py
mobileclick/utils.py
mobileclick.egg-info/PKG-INFO
mobileclick.egg-info/SOURCES.txt
mobileclick.egg-info/dependency_links.txt
mobileclick.egg-info/entry_points.txt
mobileclick.egg-info/requires.txt
mobileclick.egg-info/top_level.txt
mobileclick/methods/__init__.py
mobileclick/methods/base_ranking_method.py
mobileclick/methods/base_summarization_method.py
mobileclick/methods/lang_model.py
mobileclick/methods/lang_model_ranking_method.py
mobileclick/methods/lang_model_summarization_method.py
mobileclick/methods/lang_model_two_layer_summarization_method.py
mobileclick/methods/random_ranking_method.py
mobileclick/methods/random_summarization_method.py
mobileclick/nlp/__init__.py
mobileclick/nlp/english_parser.py
mobileclick/nlp/japanese_parser.py
mobileclick/nlp/parser.py
mobileclick/scripts/__init__.py
mobileclick/scripts/mobileclick_download_data.py
mobileclick/scripts/mobileclick_download_test_data.py
mobileclick/scripts/mobileclick_download_training_data.py
mobileclick/scripts/mobileclick_lang_model_ranking_method.py
mobileclick/scripts/mobileclick_lang_model_summarization_method.py
mobileclick/scripts/mobileclick_lang_model_two_layer_summarization_method.py
mobileclick/scripts/mobileclick_random_ranking_method.py
mobileclick/scripts/mobileclick_random_summarization_method.py
mobileclick/scripts/scriptutils.py