Metadata-Version: 1.0
Name: mobileclick
Version: 0.2.0
Summary: mobileclick provides baseline methods and utility scripts for the NTCIR-12 MobileClick-2 task
Home-page: https://github.com/mpkato/mobileclick
Author: Makoto P. Kato
Author-email: kato@dl.kuis.kyoto-u.ac.jp
License: MIT License
Platform: UNKNOWN
